{
  "VISUAL ELEMENTS": {
    "Dominant colors": [
      {
        "color": "Orange/Amber",
        "approximate_percentage": "30%"
      },
      {
        "color": "Black",
        "approximate_percentage": "30%"
      },
      {
        "color": "Gray/Monochrome",
        "approximate_percentage": "25%"
      },
      {
        "color": "Yellow",
        "approximate_percentage": "10%"
      },
      {
        "color": "Red (fire)",
        "approximate_percentage": "5%"
      }
    ],
    "Composition type": "Close-up (portrait-style split down the middle)",
    "Human presence": {
      "number_of_people": 1,
      "expression": "Distressed/surprised on left, unsettling smile on right",
      "demographics": "Anime/Vtuber female character, young adult appearance"
    },
    "Main objects/props featured": [
      "Anime-style Vtuber face split into two visual themes (color vs grayscale)"
    ],
    "Background environment": "Dark/black background with flames at the bottom"
  },
  "TEXT ELEMENTS": {
    "Text visible": "None (No visible text in the thumbnail itself)",
    "Font characteristics": "N/A",
    "Text placement within frame": "N/A",
    "Emotional/trigger words": "N/A"
  },
  "THEMATIC ELEMENTS": {
    "Overall emotional tone": "Intense, dramatic, possibly sinister. Left side shows anxiety or fear, right side gives an eerie, unsettling feeling.",
    "Visual metaphors or symbols": [
      "Split-face: Contrast between two sides of character and personality (innocent/fearful vs. sinister/psychopathic).",
      "Fire: Symbol of destruction, revelation, chaos."
    ],
    "Clickbait techniques employed": [
      "Dramatic split-face transformation to hint at a shocking reveal.",
      "Use of fire and extreme emotion to build intrigue."
    ],
    "Brand elements present": [
      "Anime/Vtuber visual style associated with the genre."
    ]
  },
  "THUMBNAIL-TITLE RELATIONSHIP": {
    "Thumbnail reinforces title by": [
      "Visually depicting the concept of 'unmasking' or revealing duality (split face).",
      "Use of dramatic and unsettling imagery to echo words like 'catastrophic,' 'exposed,' and 'psychopath' from the title."
    ],
    "Contrasts or mismatches": [
      "No visible text or reference to 'Sinder' directly, but the visual metaphor is strong.",
      "The extreme stylistic contrast may exaggerate the video's investigative or expos\u00e9 nature for dramatic effect."
    ]
  }
}