{
  "VISUAL ELEMENTS": {
    "Dominant colors": {
      "Light Pink (sweater)": "40%",
      "Light Beige (background/wall)": "30%",
      "Brown (hair)": "15%",
      "Skin tones": "10%",
      "White (cotton pad)": "5%"
    },
    "Composition type": "Medium close-up (framed from chest up, centered in vertical format)",
    "Human presence": {
      "Number of people": 1,
      "Expressions": "Neutral to slight smile, calm and composed",
      "Demographics": "Young adult female, medium complexion"
    },
    "Main objects/props featured": [
      "Cotton pad (with visible makeup residue)",
      "Pink sweater (worn by person)"
    ],
    "Background environment": "Plain indoor setting, beige wall, soft lighting"
  },
  "TEXT ELEMENTS": {
    "All text visible in the thumbnail": "use it as a makeup remover",
    "Font characteristics": {
      "Style": "Bold sans-serif",
      "Emphasis": "All lowercase, high contrast against background",
      "Color": "White text on black background bar"
    },
    "Text placement within frame": "Lower center, placed as a subtitle overlay",
    "Use of emotional/trigger words": "Practical instruction ('use it'), benefit-driven phrase ('makeup remover')"
  },
  "THEMATIC ELEMENTS": {
    "Overall emotional tone": "Helpful, practical, straightforward, slightly inviting",
    "Visual metaphors or symbols": {
      "Cotton pad with makeup": "Represents makeup removal in action, visual cue for the product\u2019s use",
      "Clean, soft color palette": "Evokes cleanliness and gentleness"
    },
    "Clickbait techniques employed": [
      "Direct benefit in text ('use it as a makeup remover')",
      "Clear demonstration of use",
      "Inclusion of person for relatability"
    ],
    "Brand elements present": "None visibly present (no logos or brand markings)"
  },
  "THUMBNAIL-TITLE RELATIONSHIP": {
    "Thumbnail supports title by": "Visually illustrating one of the ways to use baby oil (as a makeup remover), matching the 'Ways to use baby oil' theme. The cotton pad with makeup residue and the person\u2019s clean skin visually reinforce the utility described.",
    "Contrasts or mismatches": "The thumbnail shows only one specific use (makeup removal), while the title suggests multiple uses. The '#shorts' aspect is visually matched by the vertical format."
  }
}