{
  "VISUAL ELEMENTS": {
    "dominant_colors": {
      "beige/skin tones": "40%",
      "red (Canadian flag)": "25%",
      "white (flag and shirts)": "15%",
      "dark brown/blacks (background shadows and jackets)": "20%"
    },
    "composition_type": "Close-up / Medium close-up (shoulders and heads of two people dominate the frame)",
    "human_presence": {
      "number_of_people": 2,
      "expressions": [
        "Left: Neutral to slightly concerned/distant",
        "Right: Serious, stern, unsmiling"
      ],
      "demographics": "Both appear to be older white males"
    },
    "main_objects_props_featured": [
      "Two male individuals in foreground",
      "Canadian flag in the background, slightly out of focus"
    ],
    "background_environment": "Blurred, suggesting an urban or governmental building, dominated by a large Canadian flag"
  },
  "TEXT ELEMENTS": {
    "visible_text": "",
    "font_characteristics": "No text present in the thumbnail image itself",
    "text_placement_within_frame": "N/A",
    "emotional_trigger_words": "N/A"
  },
  "THEMATIC ELEMENTS": {
    "overall_emotional_tone": "Serious, tense, and contemplative. Possibly political or dealing with national decisions.",
    "visual_metaphors_or_symbols": [
      "Canadian flag as a national symbol, suggesting a focus on Canadian identity, politics, decision-making."
    ],
    "clickbait_techniques_employed": [
      "Strong, serious facial expressions to imply drama or important stakes",
      "Direct eye contact from the person on the right",
      "Contrasting expressions to hint at disagreement or choice"
    ],
    "brand_elements_present": "No explicit branding visible in the thumbnail."
  },
  "THUMBNAIL-TITLE RELATIONSHIP": {
    "visual_reinforcement": "The thumbnail shows two stern-looking men overlaid on a large Canadian flag, directly aligning with the title 'Canada Has Chosen.' This visual composition implies a major decision, possible conflict, or dichotomy\u2014the two figures potentially represent choices, sides, or key players in a Canadian context.",
    "contrasts_or_mismatches": "No apparent mismatch; the serious tone of the thumbnail matches the gravity suggested in the title."
  }
}