{
  "VISUAL ELEMENTS": {
    "Dominant colors": {
      "Orange": "30% (border, logo, text highlight)",
      "Black": "30% (shirt, text, logo, equipment)",
      "Gray": "20% (countertop, background wall, some areas of shirt and tools)",
      "White": "10% (background, light/window, text, label)",
      "Flesh tones": "10% (man's arms, face and hands)"
    },
    "Composition type": "Medium shot (waist-up view of a man in the foreground, workspace and background visible)",
    "Human presence": {
      "Number of people": 1,
      "Expressions": "Serious, focused, slightly skeptical (eyebrows raised, direct gaze at camera)",
      "Demographics": "Adult male, light skin, bald, goatee/beard"
    },
    "Main objects/props featured": [
      "Man wearing a shirt with 'URIAH' name tag and Guardian logo",
      "Various locksmith tools on the counter",
      "Key cutter machine",
      "Locksmith tool case with US flag sticker",
      "Red plastic objects/caps",
      "Workshop/locksmith shop environment"
    ],
    "Background environment": "Inside a locksmith shop with products on shelves, tools hung on a wall, large safe visible, bright window light"
  },
  "TEXT ELEMENTS": {
    "All text visible in the thumbnail": [
      "GUARDIAN SAFE & LOCK",
      "URIAH",
      "Security Myths & Locksmith Tricks - Part1"
    ],
    "Font characteristics": {
      "Style": "Bold sans-serif (Guardian logo and title), all-caps (logo), mixed case (title text)",
      "Emphasis": "High (contrast between black font and orange/white backgrounds); logo combines graphic and text elements",
      "Color": "Black (main text and logo); orange highlight/background for border and text box"
    },
    "Text placement within frame": {
      "Logo": "Top left corner",
      "Name tag": "Over man's chest, left side",
      "Video title": "Right side, inside an orange-bordered box"
    },
    "Use of emotional/trigger words": [
      "Myths",
      "Tricks"
    ]
  },
  "THEMATIC ELEMENTS": {
    "Overall emotional tone": "Authoritative and informative with a hint of skepticism/intrigue",
    "Visual metaphors or symbols": [
      "Key in logo symbolizes locksmith/security",
      "Professional setting reinforces expertise"
    ],
    "Clickbait techniques employed": [
      "Promise of exposing 'myths' and 'tricks'",
      "Direct and skeptical facial expression to intrigue viewers",
      "Use of 'Part 1' to indicate ongoing series, inviting further watching"
    ],
    "Brand elements present": [
      "GUARDIAN SAFE & LOCK logo",
      "Consistent orange-black theme"
    ]
  },
  "THUMBNAIL-TITLE RELATIONSHIP": {
    "How the thumbnail visually reinforces the title": "The presence of a professional locksmith (with tools and branded attire) aligns with the topic of 'Locksmith Tricks.' His direct and confident demeanor along with the visible tools reinforces the authority to 'debunk myths' about security, matching the promise of the title.",
    "Any contrasts or mismatches between thumbnail and title": "There are no obvious mismatches. The visual is consistent with the topic and tone suggested by the title; both emphasize expertise, knowledge, and a behind-the-scenes perspective on security."
  }
}